githubremote
githubremote-qt
setup.py
GithubRemote/__init__.py
GithubRemote/tools.py
GithubRemote.egg-info/PKG-INFO
GithubRemote.egg-info/SOURCES.txt
GithubRemote.egg-info/dependency_links.txt
GithubRemote.egg-info/requires.txt
GithubRemote.egg-info/top_level.txt
GithubRemote/Gui/AddAccountWizard.py
GithubRemote/Gui/AddRepoWizard.py
GithubRemote/Gui/Main.py
GithubRemote/Gui/__init__.py
GithubRemote/Gui/tools.py