Metadata-Version: 1.1
Name: GithubRemote
Version: 0.1.1
Summary: Access remote github repos
Home-page: https://github.com/cameronbwhite/GithubRemote
Author: Cameron Brandon White
Author-email: cameronbwhite90@gmail.com
License: BSD
Platform: UNKNOWN
Classifier: Development Status :: 3 - Alpha
Classifier: License :: OSI Approved :: BSD License
Classifier: Intended Audience :: End Users/Desktop
Classifier: Operating System :: OS Independent
Classifier: Programming Language :: Python :: 2.7
Classifier: Programming Language :: Python :: 2.6
Provides: GithubRemote
